sql_antipattern_scanner/__init__.py
sql_antipattern_scanner/antipatterns.py
sql_antipattern_scanner/cli.py
sql_antipattern_scanner/report_generator.py
sql_antipattern_scanner/sql_antipattern_scanner.py
sql_antipattern_scanner/config/config.json
sql_antipattern_scanner/static/report_styles.css
sql_antipattern_scanner/tests/test_sql_antipattern_scanner.py
sql_antipattern_scanner-0.1.3.dist-info/LICENSE
sql_antipattern_scanner-0.1.3.dist-info/METADATA
sql_antipattern_scanner-0.1.3.dist-info/WHEEL
sql_antipattern_scanner-0.1.3.dist-info/entry_points.txt
sql_antipattern_scanner-0.1.3.dist-info/top_level.txt
sql_antipattern_scanner-0.1.3.dist-info/RECORD
