Metadata-Version: 2.1
Name: sql_antipattern_scanner
Version: 0.1.3
Summary: Tool to scan SQL for antipatterns and generate reports with remediation steps
Home-page: https://github.com/npiesco/sql-antipattern-scanner
Author: Nicholas G. Piesco
Author-email: "Nicholas G. Piesco" <nicholas.piesco@gmail.com>
License: MIT
Project-URL: Homepage, https://github.com/npiesco/sql-antipattern-scanner
Project-URL: Bug Tracker, https://github.com/npiesco/sql-antipattern-scanner/issues
Classifier: Programming Language :: Python :: 3
Classifier: License :: OSI Approved :: MIT License
Classifier: Operating System :: OS Independent
Requires-Python: >=3.6
License-File: LICENSE
Requires-Dist: sqlparse
Requires-Dist: pyyaml
Requires-Dist: jinja2
Provides-Extra: test
Requires-Dist: pytest; extra == "test"
